reddel_server/__init__.py
reddel_server/__main__.py
reddel_server/cli.py
reddel_server/exceptions.py
reddel_server/provider.py
reddel_server/redlib.py
reddel_server/redprovider.py
reddel_server/server.py
reddel_server/utils.py
reddel_server/validators.py
reddel_server-0.2.0.dist-info/DESCRIPTION.rst
reddel_server-0.2.0.dist-info/METADATA
reddel_server-0.2.0.dist-info/RECORD
reddel_server-0.2.0.dist-info/WHEEL
reddel_server-0.2.0.dist-info/entry_points.txt
reddel_server-0.2.0.dist-info/metadata.json
reddel_server-0.2.0.dist-info/top_level.txt
