Metadata-Version: 2.0
Name: reddel-server
Version: 0.2.0
Summary: Python EPC server for reddel.
Home-page: https://github.com/storax/reddel-server
Author: David Zuber
Author-email: zuber.david@gmx.de
License: BSD
Platform: UNKNOWN
Classifier: Development Status :: 1 - Planning
Classifier: Intended Audience :: Developers
Classifier: License :: OSI Approved :: BSD License
Classifier: Operating System :: Unix
Classifier: Operating System :: POSIX
Classifier: Operating System :: Microsoft :: Windows
Classifier: Programming Language :: Python
Classifier: Programming Language :: Python :: 2.7
Classifier: Programming Language :: Python :: 3
Classifier: Programming Language :: Python :: 3.3
Classifier: Programming Language :: Python :: 3.4
Classifier: Programming Language :: Python :: 3.5
Classifier: Programming Language :: Python :: Implementation :: CPython
Classifier: Programming Language :: Python :: Implementation :: PyPy
Classifier: Topic :: Utilities
Requires-Dist: click
Requires-Dist: epc
Requires-Dist: redbaron
Requires-Dist: six
Requires-Dist: click-log
